{"network":[{"epi":1,"nodes":[{"name":"노을","size":4.61},{"name":"덕선","size":4.94},{"name":"덕선모","size":5.14},{"name":"덕선부","size":4.7},{"name":"동룡","size":4.38},{"name":"보라","size":4.38},{"name":"선우","size":5.14},{"name":"선우모","size":4.87},{"name":"정봉","size":3.4},{"name":"정환","size":5.14},{"name":"정환모","size":5.08},{"name":"정환부","size":4.25}],"edges":[{"source":0,"target":1,"value":6},{"source":0,"target":2,"value":9},{"source":0,"target":3,"value":7},{"source":0,"target":4,"value":1},{"source":0,"target":5,"value":7},{"source":0,"target":6,"value":1},{"source":0,"target":7,"value":1},{"source":0,"target":10,"value":1},{"source":1,"target":2,"value":8},{"source":1,"target":3,"value":8},{"source":1,"target":4,"value":3},{"source":1,"target":5,"value":6},{"source":1,"target":6,"value":3},{"source":1,"target":7,"value":1},{"source":1,"target":9,"value":4},{"source":1,"target":10,"value":1},{"source":1,"target":11,"value":1},{"source":2,"target":3,"value":8},{"source":2,"target":4,"value":2},{"source":2,"target":5,"value":7},{"source":2,"target":6,"value":3},{"source":2,"target":7,"value":5},{"source":2,"target":9,"value":3},{"source":2,"target":10,"value":7},{"source":2,"target":11,"value":2},{"source":3,"target":4,"value":1},{"source":3,"target":5,"value":6},{"source":3,"target":6,"value":1},{"source":3,"target":7,"value":1},{"source":3,"target":9,"value":1},{"source":3,"target":10,"value":1},{"source":3,"target":11,"value":1},{"source":4,"target":6,"value":7},{"source":4,"target":7,"value":2},{"source":4,"target":9,"value":7},{"source":4,"target":10,"value":2},{"source":6,"target":7,"value":10},{"source":6,"target":9,"value":7},{"source":6,"target":10,"value":5},{"source":7,"target":9,"value":2},{"source":7,"target":10,"value":6},{"source":7,"target":11,"value":2},{"source":8,"target":9,"value":3},{"source":8,"target":10,"value":3},{"source":8,"target":11,"value":3},{"source":9,"target":10,"value":10},{"source":9,"target":11,"value":4},{"source":10,"target":11,"value":6}]},{"epi":2,"nodes":[{"name":"노을","size":3.91},{"name":"덕선","size":5.67},{"name":"덕선모","size":5.01},{"name":"덕선부","size":4.79},{"name":"동룡","size":5.08},{"name":"동룡부","size":3},{"name":"미옥","size":3.4},{"name":"보라","size":4.79},{"name":"선우","size":5.3},{"name":"선우모","size":4.38},{"name":"자현","size":3.4},{"name":"정봉","size":2.3},{"name":"정환","size":5.25},{"name":"정환모","size":4.5},{"name":"정환부","size":4.25},{"name":"택이","size":3.91},{"name":"택이부","size":3.69}],"edges":[{"source":0,"target":1,"value":5},{"source":0,"target":2,"value":3},{"source":0,"target":3,"value":1},{"source":0,"target":7,"value":3},{"source":1,"target":2,"value":8},{"source":1,"target":3,"value":6},{"source":1,"target":4,"value":7},{"source":1,"target":6,"value":3},{"source":1,"target":7,"value":9},{"source":1,"target":8,"value":10},{"source":1,"target":9,"value":2},{"source":1,"target":10,"value":3},{"source":1,"target":11,"value":1},{"source":1,"target":12,"value":9},{"source":1,"target":13,"value":2},{"source":1,"target":14,"value":1},{"source":1,"target":15,"value":3},{"source":2,"target":3,"value":7},{"source":2,"target":4,"value":3},{"source":2,"target":5,"value":1},{"source":2,"target":7,"value":4},{"source":2,"target":8,"value":5},{"source":2,"target":9,"value":5},{"source":2,"target":12,"value":4},{"source":2,"target":13,"value":6},{"source":2,"target":14,"value":5},{"source":2,"target":15,"value":3},{"source":2,"target":16,"value":3},{"source":3,"target":7,"value":3},{"source":3,"target":8,"value":1},{"source":3,"target":9,"value":4},{"source":3,"target":12,"value":1},{"source":3,"target":13,"value":4},{"source":3,"target":14,"value":3},{"source":3,"target":15,"value":3},{"source":3,"target":16,"value":3},{"source":4,"target":5,"value":1},{"source":4,"target":8,"value":14},{"source":4,"target":9,"value":1},{"source":4,"target":12,"value":14},{"source":4,"target":13,"value":1},{"source":4,"target":15,"value":2},{"source":5,"target":7,"value":1},{"source":5,"target":14,"value":1},{"source":6,"target":10,"value":2},{"source":7,"target":13,"value":2},{"source":7,"target":14,"value":2},{"source":8,"target":9,"value":4},{"source":8,"target":12,"value":16},{"source":8,"target":13,"value":2},{"source":8,"target":14,"value":1},{"source":8,"target":15,"value":3},{"source":8,"target":16,"value":1},{"source":9,"target":12,"value":2},{"source":9,"target":13,"value":5},{"source":9,"target":14,"value":4},{"source":9,"target":15,"value":1},{"source":9,"target":16,"value":4},{"source":11,"target":12,"value":1},{"source":11,"target":13,"value":1},{"source":11,"target":14,"value":1},{"source":12,"target":13,"value":4},{"source":12,"target":14,"value":2},{"source":12,"target":15,"value":3},{"source":12,"target":16,"value":1},{"source":13,"target":14,"value":5},{"source":13,"target":15,"value":1},{"source":13,"target":16,"value":3},{"source":14,"target":15,"value":1},{"source":14,"target":16,"value":4},{"source":15,"target":16,"value":1}]},{"epi":3,"nodes":[{"name":"노을","size":3.91},{"name":"덕선","size":5.25},{"name":"덕선모","size":4.7},{"name":"덕선부","size":4.7},{"name":"동룡","size":4.09},{"name":"동룡부","size":2.3},{"name":"미옥","size":4.38},{"name":"보라","size":3.69},{"name":"선우","size":4.25},{"name":"선우모","size":3},{"name":"자현","size":4.38},{"name":"정봉","size":3},{"name":"정환","size":4.38},{"name":"정환모","size":4.5},{"name":"정환부","size":4.25},{"name":"택이","size":3},{"name":"택이부","size":2.3}],"edges":[{"source":0,"target":1,"value":3},{"source":0,"target":2,"value":1},{"source":0,"target":3,"value":4},{"source":0,"target":7,"value":2},{"source":0,"target":8,"value":1},{"source":1,"target":2,"value":5},{"source":1,"target":3,"value":4},{"source":1,"target":4,"value":6},{"source":1,"target":5,"value":1},{"source":1,"target":6,"value":8},{"source":1,"target":7,"value":4},{"source":1,"target":8,"value":6},{"source":1,"target":10,"value":8},{"source":1,"target":12,"value":7},{"source":1,"target":13,"value":1},{"source":1,"target":15,"value":1},{"source":2,"target":3,"value":8},{"source":2,"target":7,"value":3},{"source":2,"target":8,"value":1},{"source":2,"target":9,"value":1},{"source":2,"target":12,"value":1},{"source":2,"target":13,"value":3},{"source":2,"target":14,"value":1},{"source":3,"target":7,"value":3},{"source":3,"target":8,"value":1},{"source":3,"target":9,"value":1},{"source":3,"target":12,"value":1},{"source":3,"target":13,"value":1},{"source":3,"target":14,"value":1},{"source":4,"target":5,"value":1},{"source":4,"target":6,"value":2},{"source":4,"target":8,"value":5},{"source":4,"target":10,"value":2},{"source":4,"target":12,"value":6},{"source":4,"target":15,"value":1},{"source":5,"target":8,"value":1},{"source":5,"target":12,"value":1},{"source":6,"target":8,"value":2},{"source":6,"target":10,"value":8},{"source":6,"target":12,"value":2},{"source":7,"target":8,"value":1},{"source":7,"target":13,"value":1},{"source":8,"target":9,"value":1},{"source":8,"target":10,"value":2},{"source":8,"target":12,"value":5},{"source":8,"target":15,"value":1},{"source":9,"target":13,"value":1},{"source":9,"target":14,"value":1},{"source":10,"target":12,"value":2},{"source":11,"target":12,"value":1},{"source":11,"target":13,"value":2},{"source":11,"target":14,"value":2},{"source":12,"target":13,"value":1},{"source":12,"target":14,"value":1},{"source":12,"target":15,"value":1},{"source":13,"target":14,"value":7},{"source":15,"target":16,"value":1}]},{"epi":4,"nodes":[{"name":"노을","size":3.69},{"name":"덕선","size":5.19},{"name":"덕선모","size":4.79},{"name":"덕선부","size":4.61},{"name":"동룡","size":4.61},{"name":"보라","size":4.09},{"name":"선우","size":4.61},{"name":"선우모","size":4.09},{"name":"정봉","size":3.4},{"name":"정환","size":5.14},{"name":"정환모","size":4.79},{"name":"정환부","size":4.7},{"name":"택이","size":4.09},{"name":"택이부","size":3.69}],"edges":[{"source":0,"target":1,"value":3},{"source":0,"target":2,"value":4},{"source":0,"target":3,"value":4},{"source":0,"target":5,"value":2},{"source":1,"target":2,"value":3},{"source":1,"target":3,"value":4},{"source":1,"target":4,"value":8},{"source":1,"target":5,"value":6},{"source":1,"target":6,"value":6},{"source":1,"target":7,"value":1},{"source":1,"target":8,"value":1},{"source":1,"target":9,"value":8},{"source":1,"target":12,"value":4},{"source":1,"target":13,"value":2},{"source":2,"target":3,"value":9},{"source":2,"target":5,"value":2},{"source":2,"target":7,"value":1},{"source":2,"target":10,"value":3},{"source":2,"target":11,"value":2},{"source":2,"target":12,"value":1},{"source":2,"target":13,"value":1},{"source":3,"target":5,"value":2},{"source":3,"target":10,"value":1},{"source":3,"target":11,"value":1},{"source":3,"target":12,"value":1},{"source":4,"target":5,"value":3},{"source":4,"target":6,"value":6},{"source":4,"target":8,"value":1},{"source":4,"target":9,"value":6},{"source":4,"target":12,"value":2},{"source":4,"target":13,"value":2},{"source":5,"target":6,"value":1},{"source":5,"target":8,"value":1},{"source":5,"target":9,"value":1},{"source":6,"target":7,"value":3},{"source":6,"target":9,"value":4},{"source":6,"target":12,"value":2},{"source":6,"target":13,"value":2},{"source":7,"target":9,"value":1},{"source":7,"target":10,"value":1},{"source":7,"target":13,"value":2},{"source":8,"target":9,"value":3},{"source":8,"target":10,"value":1},{"source":8,"target":11,"value":1},{"source":9,"target":10,"value":6},{"source":9,"target":11,"value":7},{"source":9,"target":12,"value":2},{"source":9,"target":13,"value":2},{"source":10,"target":11,"value":9},{"source":10,"target":12,"value":1},{"source":10,"target":13,"value":1},{"source":12,"target":13,"value":1}]},{"epi":5,"nodes":[{"name":"노을","size":4.38},{"name":"덕선","size":4.61},{"name":"덕선모","size":5.01},{"name":"덕선부","size":4.7},{"name":"동룡","size":3.69},{"name":"미옥","size":2.3},{"name":"보라","size":4.09},{"name":"선우","size":4.7},{"name":"선우모","size":4.87},{"name":"자현","size":2.3},{"name":"정봉","size":4.61},{"name":"정환","size":5.19},{"name":"정환모","size":4.87},{"name":"정환부","size":5.01},{"name":"택이","size":3.4},{"name":"택이부","size":3}],"edges":[{"source":0,"target":1,"value":5},{"source":0,"target":2,"value":7},{"source":0,"target":3,"value":7},{"source":0,"target":6,"value":2},{"source":1,"target":2,"value":6},{"source":1,"target":3,"value":4},{"source":1,"target":4,"value":1},{"source":1,"target":5,"value":1},{"source":1,"target":6,"value":2},{"source":1,"target":7,"value":2},{"source":1,"target":9,"value":1},{"source":1,"target":11,"value":3},{"source":1,"target":14,"value":1},{"source":2,"target":3,"value":8},{"source":2,"target":6,"value":4},{"source":2,"target":8,"value":3},{"source":2,"target":12,"value":1},{"source":2,"target":13,"value":2},{"source":2,"target":15,"value":1},{"source":3,"target":6,"value":4},{"source":3,"target":13,"value":2},{"source":3,"target":15,"value":1},{"source":4,"target":7,"value":1},{"source":4,"target":11,"value":4},{"source":5,"target":9,"value":1},{"source":6,"target":8,"value":1},{"source":6,"target":13,"value":1},{"source":6,"target":15,"value":1},{"source":7,"target":8,"value":7},{"source":7,"target":10,"value":1},{"source":7,"target":11,"value":5},{"source":7,"target":14,"value":1},{"source":8,"target":10,"value":1},{"source":8,"target":11,"value":1},{"source":8,"target":12,"value":2},{"source":8,"target":13,"value":1},{"source":10,"target":11,"value":8},{"source":10,"target":12,"value":5},{"source":10,"target":13,"value":8},{"source":11,"target":12,"value":6},{"source":11,"target":13,"value":8},{"source":11,"target":14,"value":2},{"source":12,"target":13,"value":7},{"source":12,"target":14,"value":2},{"source":12,"target":15,"value":1},{"source":13,"target":15,"value":1},{"source":14,"target":15,"value":1}]},{"epi":6,"nodes":[{"name":"노을","size":3.4},{"name":"덕선","size":5.6},{"name":"덕선모","size":4.61},{"name":"덕선부","size":4.38},{"name":"동룡","size":4.61},{"name":"동룡부","size":2.3},{"name":"미옥","size":2.3},{"name":"보라","size":4.87},{"name":"선우","size":5.14},{"name":"선우모","size":4.09},{"name":"자현","size":2.3},{"name":"정봉","size":3.4},{"name":"정환","size":4.87},{"name":"정환모","size":4.38},{"name":"정환부","size":3.69},{"name":"택이","size":4.09},{"name":"택이부","size":4.61}],"edges":[{"source":0,"target":1,"value":2},{"source":0,"target":2,"value":2},{"source":0,"target":3,"value":2},{"source":0,"target":7,"value":3},{"source":1,"target":2,"value":9},{"source":1,"target":3,"value":5},{"source":1,"target":4,"value":6},{"source":1,"target":5,"value":1},{"source":1,"target":6,"value":1},{"source":1,"target":7,"value":6},{"source":1,"target":8,"value":11},{"source":1,"target":10,"value":1},{"source":1,"target":12,"value":7},{"source":1,"target":13,"value":2},{"source":1,"target":15,"value":2},{"source":1,"target":16,"value":4},{"source":2,"target":3,"value":4},{"source":2,"target":7,"value":4},{"source":2,"target":9,"value":1},{"source":2,"target":13,"value":1},{"source":2,"target":14,"value":1},{"source":2,"target":16,"value":1},{"source":3,"target":4,"value":1},{"source":3,"target":5,"value":1},{"source":3,"target":7,"value":3},{"source":3,"target":8,"value":1},{"source":3,"target":9,"value":1},{"source":3,"target":12,"value":1},{"source":3,"target":13,"value":1},{"source":3,"target":14,"value":2},{"source":3,"target":16,"value":5},{"source":4,"target":5,"value":1},{"source":4,"target":8,"value":8},{"source":4,"target":12,"value":6},{"source":4,"target":15,"value":4},{"source":4,"target":16,"value":2},{"source":5,"target":8,"value":1},{"source":5,"target":12,"value":1},{"source":5,"target":16,"value":1},{"source":6,"target":10,"value":1},{"source":7,"target":8,"value":4},{"source":7,"target":9,"value":3},{"source":7,"target":11,"value":1},{"source":7,"target":13,"value":1},{"source":7,"target":14,"value":1},{"source":7,"target":16,"value":1},{"source":8,"target":9,"value":2},{"source":8,"target":12,"value":7},{"source":8,"target":15,"value":2},{"source":8,"target":16,"value":3},{"source":9,"target":12,"value":1},{"source":9,"target":13,"value":1},{"source":9,"target":14,"value":1},{"source":9,"target":16,"value":2},{"source":11,"target":12,"value":1},{"source":11,"target":13,"value":2},{"source":11,"target":14,"value":1},{"source":12,"target":13,"value":6},{"source":12,"target":14,"value":2},{"source":12,"target":15,"value":2},{"source":12,"target":16,"value":2},{"source":13,"target":14,"value":3},{"source":13,"target":16,"value":1},{"source":14,"target":16,"value":2},{"source":15,"target":16,"value":2}]},{"epi":7,"nodes":[{"name":"노을","size":4.38},{"name":"덕선","size":5.25},{"name":"덕선모","size":4.61},{"name":"덕선부","size":4.61},{"name":"동룡","size":4.09},{"name":"동룡부","size":3.69},{"name":"미옥","size":3},{"name":"보라","size":4.38},{"name":"선우","size":5.08},{"name":"선우모","size":4.87},{"name":"자현","size":3},{"name":"정봉","size":3.91},{"name":"정환","size":4.7},{"name":"정환모","size":4.7},{"name":"정환부","size":4.25},{"name":"택이","size":4.38},{"name":"택이부","size":4.79}],"edges":[{"source":0,"target":1,"value":7},{"source":0,"target":2,"value":1},{"source":0,"target":3,"value":1},{"source":0,"target":4,"value":5},{"source":0,"target":7,"value":4},{"source":0,"target":8,"value":3},{"source":0,"target":11,"value":5},{"source":0,"target":12,"value":3},{"source":0,"target":15,"value":2},{"source":1,"target":2,"value":3},{"source":1,"target":3,"value":2},{"source":1,"target":4,"value":4},{"source":1,"target":6,"value":2},{"source":1,"target":7,"value":4},{"source":1,"target":8,"value":6},{"source":1,"target":9,"value":1},{"source":1,"target":10,"value":2},{"source":1,"target":11,"value":4},{"source":1,"target":12,"value":8},{"source":1,"target":13,"value":1},{"source":1,"target":14,"value":1},{"source":1,"target":15,"value":5},{"source":1,"target":16,"value":2},{"source":2,"target":3,"value":7},{"source":2,"target":5,"value":3},{"source":2,"target":7,"value":2},{"source":2,"target":8,"value":1},{"source":2,"target":9,"value":6},{"source":2,"target":13,"value":6},{"source":2,"target":14,"value":4},{"source":2,"target":15,"value":1},{"source":2,"target":16,"value":4},{"source":3,"target":5,"value":4},{"source":3,"target":7,"value":1},{"source":3,"target":8,"value":1},{"source":3,"target":9,"value":6},{"source":3,"target":13,"value":5},{"source":3,"target":14,"value":7},{"source":3,"target":15,"value":1},{"source":3,"target":16,"value":4},{"source":4,"target":7,"value":3},{"source":4,"target":8,"value":4},{"source":4,"target":11,"value":5},{"source":4,"target":12,"value":3},{"source":4,"target":15,"value":1},{"source":5,"target":9,"value":4},{"source":5,"target":13,"value":4},{"source":5,"target":14,"value":4},{"source":5,"target":16,"value":3},{"source":6,"target":10,"value":2},{"source":6,"target":12,"value":1},{"source":7,"target":8,"value":4},{"source":7,"target":11,"value":3},{"source":7,"target":12,"value":1},{"source":7,"target":15,"value":2},{"source":8,"target":9,"value":4},{"source":8,"target":11,"value":3},{"source":8,"target":12,"value":7},{"source":8,"target":13,"value":4},{"source":8,"target":14,"value":1},{"source":8,"target":15,"value":1},{"source":9,"target":13,"value":9},{"source":9,"target":14,"value":5},{"source":9,"target":16,"value":5},{"source":10,"target":12,"value":1},{"source":11,"target":12,"value":3},{"source":11,"target":15,"value":1},{"source":12,"target":13,"value":1},{"source":12,"target":15,"value":1},{"source":12,"target":16,"value":1},{"source":13,"target":14,"value":5},{"source":13,"target":16,"value":4},{"source":14,"target":16,"value":4},{"source":15,"target":16,"value":4}]},{"epi":8,"nodes":[{"name":"노을","size":4.25},{"name":"덕선","size":5.19},{"name":"덕선모","size":4.94},{"name":"덕선부","size":4.25},{"name":"동룡","size":4.25},{"name":"동룡부","size":2.3},{"name":"미옥","size":3},{"name":"보라","size":4.61},{"name":"선우","size":4.61},{"name":"선우모","size":3.91},{"name":"자현","size":3},{"name":"정봉","size":4.5},{"name":"정환","size":4.87},{"name":"정환모","size":4.94},{"name":"정환부","size":4.87},{"name":"택이","size":3.69},{"name":"택이부","size":3}],"edges":[{"source":0,"target":1,"value":7},{"source":0,"target":2,"value":5},{"source":0,"target":3,"value":4},{"source":0,"target":5,"value":1},{"source":0,"target":7,"value":2},{"source":1,"target":2,"value":8},{"source":1,"target":3,"value":5},{"source":1,"target":4,"value":4},{"source":1,"target":5,"value":1},{"source":1,"target":6,"value":2},{"source":1,"target":7,"value":5},{"source":1,"target":8,"value":3},{"source":1,"target":10,"value":2},{"source":1,"target":12,"value":3},{"source":1,"target":15,"value":3},{"source":2,"target":3,"value":6},{"source":2,"target":5,"value":1},{"source":2,"target":7,"value":5},{"source":2,"target":9,"value":4},{"source":2,"target":13,"value":3},{"source":2,"target":14,"value":1},{"source":2,"target":16,"value":1},{"source":3,"target":5,"value":1},{"source":3,"target":7,"value":3},{"source":3,"target":8,"value":1},{"source":3,"target":14,"value":1},{"source":3,"target":16,"value":1},{"source":4,"target":7,"value":1},{"source":4,"target":8,"value":6},{"source":4,"target":12,"value":6},{"source":4,"target":15,"value":3},{"source":6,"target":10,"value":2},{"source":7,"target":8,"value":4},{"source":7,"target":12,"value":1},{"source":7,"target":14,"value":1},{"source":7,"target":16,"value":1},{"source":8,"target":9,"value":1},{"source":8,"target":12,"value":6},{"source":8,"target":14,"value":1},{"source":8,"target":15,"value":3},{"source":8,"target":16,"value":1},{"source":9,"target":13,"value":3},{"source":9,"target":14,"value":1},{"source":9,"target":16,"value":1},{"source":11,"target":12,"value":6},{"source":11,"target":13,"value":8},{"source":11,"target":14,"value":8},{"source":12,"target":13,"value":6},{"source":12,"target":14,"value":6},{"source":12,"target":15,"value":3},{"source":13,"target":14,"value":11},{"source":14,"target":16,"value":2}]},{"epi":9,"nodes":[{"name":"노을","size":4.09},{"name":"덕선","size":5.01},{"name":"덕선모","size":4.87},{"name":"덕선부","size":4.5},{"name":"동룡","size":3},{"name":"보라","size":3},{"name":"선우","size":4.5},{"name":"선우모","size":4.94},{"name":"정환","size":3.91},{"name":"정환모","size":4.25},{"name":"택이","size":4.7},{"name":"택이부","size":4.61}],"edges":[{"source":0,"target":1,"value":3},{"source":0,"target":2,"value":4},{"source":0,"target":3,"value":3},{"source":0,"target":6,"value":1},{"source":0,"target":10,"value":1},{"source":1,"target":2,"value":3},{"source":1,"target":3,"value":1},{"source":1,"target":4,"value":1},{"source":1,"target":5,"value":1},{"source":1,"target":6,"value":2},{"source":1,"target":8,"value":3},{"source":1,"target":9,"value":1},{"source":1,"target":10,"value":10},{"source":2,"target":3,"value":8},{"source":2,"target":7,"value":2},{"source":2,"target":9,"value":2},{"source":2,"target":10,"value":3},{"source":2,"target":11,"value":2},{"source":3,"target":10,"value":1},{"source":3,"target":11,"value":3},{"source":4,"target":6,"value":2},{"source":4,"target":8,"value":1},{"source":4,"target":10,"value":1},{"source":5,"target":6,"value":2},{"source":6,"target":7,"value":2},{"source":6,"target":8,"value":3},{"source":6,"target":9,"value":1},{"source":6,"target":10,"value":1},{"source":7,"target":9,"value":4},{"source":7,"target":11,"value":7},{"source":8,"target":9,"value":1},{"source":8,"target":10,"value":1},{"source":9,"target":10,"value":1},{"source":10,"target":11,"value":1}]},{"epi":10,"nodes":[{"name":"노을","size":2.3},{"name":"덕선","size":5.19},{"name":"덕선모","size":3.4},{"name":"덕선부","size":2.3},{"name":"동룡","size":4.25},{"name":"동룡부","size":2.3},{"name":"미옥","size":3.69},{"name":"보라","size":4.38},{"name":"선우","size":4.61},{"name":"선우모","size":3.69},{"name":"정봉","size":3.91},{"name":"정환","size":5.3},{"name":"정환모","size":4.94},{"name":"정환부","size":4.5},{"name":"택이","size":4.09},{"name":"택이부","size":3.4}],"edges":[{"source":0,"target":1,"value":1},{"source":0,"target":2,"value":1},{"source":1,"target":2,"value":2},{"source":1,"target":3,"value":1},{"source":1,"target":4,"value":2},{"source":1,"target":6,"value":3},{"source":1,"target":7,"value":2},{"source":1,"target":8,"value":4},{"source":1,"target":10,"value":2},{"source":1,"target":11,"value":9},{"source":1,"target":12,"value":3},{"source":1,"target":13,"value":1},{"source":1,"target":14,"value":6},{"source":2,"target":3,"value":1},{"source":2,"target":9,"value":1},{"source":2,"target":10,"value":1},{"source":2,"target":11,"value":1},{"source":2,"target":12,"value":2},{"source":3,"target":10,"value":1},{"source":3,"target":11,"value":1},{"source":3,"target":12,"value":1},{"source":4,"target":5,"value":1},{"source":4,"target":7,"value":2},{"source":4,"target":8,"value":4},{"source":4,"target":11,"value":6},{"source":4,"target":12,"value":1},{"source":4,"target":14,"value":2},{"source":5,"target":11,"value":1},{"source":6,"target":10,"value":1},{"source":6,"target":11,"value":1},{"source":7,"target":8,"value":6},{"source":7,"target":11,"value":4},{"source":7,"target":14,"value":1},{"source":8,"target":11,"value":5},{"source":8,"target":12,"value":1},{"source":8,"target":14,"value":3},{"source":9,"target":12,"value":1},{"source":9,"target":15,"value":3},{"source":10,"target":11,"value":3},{"source":10,"target":12,"value":4},{"source":10,"target":13,"value":2},{"source":11,"target":12,"value":6},{"source":11,"target":13,"value":4},{"source":11,"target":14,"value":2},{"source":12,"target":13,"value":9},{"source":12,"target":14,"value":1}]},{"epi":11,"nodes":[{"name":"노을","size":4.79},{"name":"덕선","size":5.3},{"name":"덕선모","size":5.52},{"name":"덕선부","size":5.01},{"name":"동룡","size":4.09},{"name":"동룡부","size":4.09},{"name":"미옥","size":2.3},{"name":"보라","size":4.5},{"name":"선우","size":4.87},{"name":"선우모","size":5.08},{"name":"자현","size":2.3},{"name":"정봉","size":5.01},{"name":"정환","size":5.14},{"name":"정환모","size":5.7},{"name":"정환부","size":5.35},{"name":"택이","size":3.91},{"name":"택이부","size":4.38}],"edges":[{"source":0,"target":1,"value":6},{"source":0,"target":2,"value":5},{"source":0,"target":3,"value":5},{"source":0,"target":7,"value":5},{"source":0,"target":8,"value":5},{"source":0,"target":9,"value":4},{"source":0,"target":11,"value":5},{"source":0,"target":12,"value":2},{"source":0,"target":13,"value":2},{"source":0,"target":14,"value":1},{"source":1,"target":2,"value":6},{"source":1,"target":3,"value":3},{"source":1,"target":4,"value":2},{"source":1,"target":6,"value":1},{"source":1,"target":7,"value":4},{"source":1,"target":8,"value":2},{"source":1,"target":9,"value":3},{"source":1,"target":10,"value":1},{"source":1,"target":11,"value":2},{"source":1,"target":12,"value":7},{"source":1,"target":13,"value":2},{"source":1,"target":14,"value":2},{"source":1,"target":15,"value":4},{"source":1,"target":16,"value":1},{"source":2,"target":3,"value":10},{"source":2,"target":5,"value":3},{"source":2,"target":7,"value":4},{"source":2,"target":8,"value":2},{"source":2,"target":9,"value":7},{"source":2,"target":11,"value":4},{"source":2,"target":12,"value":4},{"source":2,"target":13,"value":18},{"source":2,"target":14,"value":9},{"source":2,"target":16,"value":2},{"source":3,"target":4,"value":1},{"source":3,"target":5,"value":4},{"source":3,"target":7,"value":2},{"source":3,"target":8,"value":1},{"source":3,"target":9,"value":2},{"source":3,"target":11,"value":1},{"source":3,"target":13,"value":6},{"source":3,"target":14,"value":5},{"source":4,"target":5,"value":1},{"source":4,"target":8,"value":1},{"source":4,"target":12,"value":2},{"source":5,"target":13,"value":4},{"source":5,"target":14,"value":2},{"source":6,"target":10,"value":1},{"source":7,"target":8,"value":6},{"source":7,"target":9,"value":1},{"source":7,"target":11,"value":3},{"source":7,"target":12,"value":2},{"source":7,"target":13,"value":1},{"source":7,"target":14,"value":1},{"source":8,"target":9,"value":7},{"source":8,"target":11,"value":3},{"source":8,"target":12,"value":1},{"source":8,"target":13,"value":1},{"source":8,"target":14,"value":1},{"source":8,"target":15,"value":1},{"source":8,"target":16,"value":2},{"source":9,"target":11,"value":1},{"source":9,"target":12,"value":1},{"source":9,"target":13,"value":5},{"source":9,"target":14,"value":3},{"source":9,"target":15,"value":1},{"source":9,"target":16,"value":6},{"source":11,"target":12,"value":3},{"source":11,"target":13,"value":7},{"source":11,"target":14,"value":7},{"source":12,"target":13,"value":7},{"source":12,"target":14,"value":2},{"source":12,"target":16,"value":1},{"source":13,"target":14,"value":16},{"source":13,"target":16,"value":2},{"source":14,"target":16,"value":2},{"source":15,"target":16,"value":1}]},{"epi":12,"nodes":[{"name":"노을","size":4.38},{"name":"덕선","size":5.44},{"name":"덕선모","size":3.91},{"name":"덕선부","size":3.69},{"name":"동룡","size":5.01},{"name":"동룡부","size":3.4},{"name":"보라","size":4.87},{"name":"선우","size":5.63},{"name":"선우모","size":5.08},{"name":"자현","size":2.3},{"name":"정봉","size":4.09},{"name":"정환","size":5.08},{"name":"정환모","size":3.91},{"name":"정환부","size":3},{"name":"택이","size":4.87},{"name":"택이부","size":4.09}],"edges":[{"source":0,"target":1,"value":1},{"source":0,"target":2,"value":2},{"source":0,"target":3,"value":4},{"source":0,"target":6,"value":2},{"source":0,"target":7,"value":1},{"source":0,"target":14,"value":1},{"source":1,"target":2,"value":1},{"source":1,"target":4,"value":9},{"source":1,"target":5,"value":1},{"source":1,"target":6,"value":3},{"source":1,"target":7,"value":2},{"source":1,"target":9,"value":1},{"source":1,"target":10,"value":3},{"source":1,"target":11,"value":8},{"source":1,"target":12,"value":2},{"source":1,"target":13,"value":2},{"source":1,"target":14,"value":11},{"source":2,"target":3,"value":1},{"source":2,"target":6,"value":1},{"source":2,"target":8,"value":2},{"source":2,"target":10,"value":1},{"source":2,"target":12,"value":2},{"source":4,"target":5,"value":2},{"source":4,"target":7,"value":7},{"source":4,"target":11,"value":11},{"source":4,"target":14,"value":7},{"source":5,"target":6,"value":1},{"source":5,"target":7,"value":2},{"source":5,"target":11,"value":2},{"source":6,"target":7,"value":9},{"source":6,"target":8,"value":2},{"source":6,"target":14,"value":1},{"source":7,"target":8,"value":11},{"source":7,"target":11,"value":8},{"source":7,"target":14,"value":4},{"source":7,"target":15,"value":4},{"source":8,"target":10,"value":2},{"source":8,"target":12,"value":3},{"source":8,"target":15,"value":5},{"source":10,"target":11,"value":3},{"source":10,"target":12,"value":3},{"source":10,"target":13,"value":2},{"source":11,"target":12,"value":1},{"source":11,"target":13,"value":2},{"source":11,"target":14,"value":4},{"source":12,"target":13,"value":1}]},{"epi":13,"nodes":[{"name":"노을","size":4.09},{"name":"덕선","size":4.94},{"name":"덕선모","size":5.19},{"name":"덕선부","size":5.3},{"name":"동룡","size":3.91},{"name":"동룡부","size":3.4},{"name":"보라","size":4.7},{"name":"선우","size":4.79},{"name":"선우모","size":4.79},{"name":"자현","size":2.3},{"name":"정봉","size":3.69},{"name":"정환","size":3.91},{"name":"정환모","size":5.08},{"name":"정환부","size":5.19},{"name":"택이","size":4.09},{"name":"택이부","size":4.87}],"edges":[{"source":0,"target":1,"value":6},{"source":0,"target":2,"value":4},{"source":0,"target":3,"value":3},{"source":0,"target":4,"value":1},{"source":0,"target":6,"value":3},{"source":0,"target":10,"value":1},{"source":1,"target":2,"value":5},{"source":1,"target":3,"value":4},{"source":1,"target":4,"value":4},{"source":1,"target":5,"value":1},{"source":1,"target":6,"value":3},{"source":1,"target":7,"value":1},{"source":1,"target":8,"value":1},{"source":1,"target":9,"value":1},{"source":1,"target":10,"value":3},{"source":1,"target":11,"value":3},{"source":1,"target":12,"value":1},{"source":1,"target":13,"value":1},{"source":1,"target":14,"value":2},{"source":1,"target":15,"value":4},{"source":2,"target":3,"value":13},{"source":2,"target":4,"value":1},{"source":2,"target":5,"value":2},{"source":2,"target":6,"value":5},{"source":2,"target":8,"value":5},{"source":2,"target":10,"value":1},{"source":2,"target":11,"value":1},{"source":2,"target":12,"value":10},{"source":2,"target":13,"value":6},{"source":2,"target":15,"value":2},{"source":3,"target":4,"value":1},{"source":3,"target":5,"value":2},{"source":3,"target":6,"value":7},{"source":3,"target":8,"value":1},{"source":3,"target":10,"value":1},{"source":3,"target":11,"value":1},{"source":3,"target":12,"value":6},{"source":3,"target":13,"value":12},{"source":3,"target":15,"value":2},{"source":4,"target":5,"value":2},{"source":4,"target":7,"value":1},{"source":4,"target":8,"value":1},{"source":4,"target":10,"value":3},{"source":4,"target":11,"value":1},{"source":4,"target":12,"value":1},{"source":4,"target":13,"value":1},{"source":4,"target":15,"value":3},{"source":5,"target":8,"value":1},{"source":5,"target":10,"value":1},{"source":5,"target":11,"value":1},{"source":5,"target":12,"value":2},{"source":5,"target":13,"value":2},{"source":5,"target":15,"value":1},{"source":6,"target":7,"value":4},{"source":6,"target":12,"value":1},{"source":6,"target":13,"value":2},{"source":6,"target":15,"value":1},{"source":7,"target":8,"value":6},{"source":7,"target":14,"value":2},{"source":7,"target":15,"value":5},{"source":8,"target":10,"value":1},{"source":8,"target":11,"value":1},{"source":8,"target":12,"value":5},{"source":8,"target":13,"value":1},{"source":8,"target":14,"value":1},{"source":8,"target":15,"value":7},{"source":10,"target":11,"value":1},{"source":10,"target":12,"value":2},{"source":10,"target":13,"value":2},{"source":10,"target":15,"value":2},{"source":11,"target":12,"value":3},{"source":11,"target":13,"value":3},{"source":11,"target":15,"value":1},{"source":12,"target":13,"value":12},{"source":12,"target":15,"value":2},{"source":13,"target":15,"value":2},{"source":14,"target":15,"value":4}]},{"epi":14,"nodes":[{"name":"노을","size":4.25},{"name":"덕선","size":5.44},{"name":"덕선모","size":4.61},{"name":"덕선부","size":4.09},{"name":"동룡","size":3.69},{"name":"동룡부","size":2.3},{"name":"미옥","size":4.79},{"name":"보라","size":4.94},{"name":"선우","size":5.48},{"name":"선우모","size":4.61},{"name":"자현","size":4.25},{"name":"정봉","size":4.5},{"name":"정환","size":4.61},{"name":"정환모","size":3.4},{"name":"정환부","size":3.91},{"name":"택이","size":4.61},{"name":"택이부","size":4.25}],"edges":[{"source":0,"target":1,"value":6},{"source":0,"target":2,"value":3},{"source":0,"target":3,"value":2},{"source":0,"target":7,"value":3},{"source":0,"target":15,"value":1},{"source":1,"target":2,"value":4},{"source":1,"target":3,"value":2},{"source":1,"target":4,"value":2},{"source":1,"target":6,"value":8},{"source":1,"target":7,"value":2},{"source":1,"target":8,"value":1},{"source":1,"target":10,"value":7},{"source":1,"target":12,"value":4},{"source":1,"target":14,"value":1},{"source":1,"target":15,"value":4},{"source":1,"target":16,"value":1},{"source":2,"target":3,"value":5},{"source":2,"target":7,"value":5},{"source":2,"target":13,"value":1},{"source":2,"target":14,"value":1},{"source":3,"target":6,"value":1},{"source":3,"target":7,"value":3},{"source":3,"target":10,"value":1},{"source":4,"target":5,"value":1},{"source":4,"target":8,"value":2},{"source":4,"target":12,"value":2},{"source":4,"target":15,"value":3},{"source":4,"target":16,"value":2},{"source":5,"target":8,"value":1},{"source":5,"target":12,"value":1},{"source":6,"target":10,"value":6},{"source":6,"target":11,"value":4},{"source":7,"target":8,"value":9},{"source":7,"target":15,"value":1},{"source":7,"target":16,"value":1},{"source":8,"target":9,"value":10},{"source":8,"target":12,"value":2},{"source":8,"target":15,"value":5},{"source":8,"target":16,"value":6},{"source":9,"target":15,"value":1},{"source":9,"target":16,"value":3},{"source":11,"target":12,"value":4},{"source":11,"target":13,"value":1},{"source":11,"target":14,"value":2},{"source":12,"target":13,"value":2},{"source":12,"target":14,"value":3},{"source":12,"target":15,"value":2},{"source":12,"target":16,"value":1},{"source":13,"target":14,"value":3},{"source":13,"target":15,"value":1},{"source":14,"target":15,"value":1},{"source":15,"target":16,"value":2}]},{"epi":15,"nodes":[{"name":"노을","size":3.4},{"name":"덕선","size":5.19},{"name":"덕선모","size":4.7},{"name":"덕선부","size":4.61},{"name":"동룡","size":4.94},{"name":"동룡부","size":3},{"name":"미옥","size":3},{"name":"보라","size":5.01},{"name":"선우","size":5.35},{"name":"선우모","size":4.25},{"name":"정봉","size":4.25},{"name":"정환","size":4.87},{"name":"정환모","size":4.61},{"name":"정환부","size":4.09},{"name":"택이","size":4.38},{"name":"택이부","size":4.87}],"edges":[{"source":0,"target":1,"value":3},{"source":0,"target":2,"value":2},{"source":0,"target":3,"value":2},{"source":0,"target":4,"value":1},{"source":0,"target":7,"value":3},{"source":0,"target":8,"value":1},{"source":0,"target":10,"value":1},{"source":0,"target":11,"value":1},{"source":1,"target":2,"value":5},{"source":1,"target":3,"value":4},{"source":1,"target":4,"value":9},{"source":1,"target":5,"value":1},{"source":1,"target":6,"value":1},{"source":1,"target":7,"value":6},{"source":1,"target":8,"value":8},{"source":1,"target":10,"value":2},{"source":1,"target":11,"value":6},{"source":1,"target":14,"value":4},{"source":1,"target":15,"value":1},{"source":2,"target":3,"value":8},{"source":2,"target":7,"value":6},{"source":2,"target":9,"value":1},{"source":2,"target":12,"value":1},{"source":2,"target":15,"value":1},{"source":3,"target":7,"value":6},{"source":3,"target":10,"value":1},{"source":3,"target":11,"value":1},{"source":3,"target":12,"value":1},{"source":3,"target":13,"value":1},{"source":3,"target":15,"value":1},{"source":4,"target":5,"value":2},{"source":4,"target":7,"value":4},{"source":4,"target":8,"value":10},{"source":4,"target":10,"value":3},{"source":4,"target":11,"value":8},{"source":4,"target":12,"value":1},{"source":4,"target":14,"value":2},{"source":5,"target":8,"value":1},{"source":5,"target":11,"value":1},{"source":6,"target":10,"value":1},{"source":7,"target":8,"value":6},{"source":7,"target":10,"value":2},{"source":7,"target":11,"value":1},{"source":7,"target":12,"value":1},{"source":8,"target":9,"value":3},{"source":8,"target":10,"value":2},{"source":8,"target":11,"value":7},{"source":8,"target":14,"value":4},{"source":8,"target":15,"value":4},{"source":9,"target":12,"value":1},{"source":9,"target":15,"value":4},{"source":10,"target":11,"value":3},{"source":10,"target":12,"value":4},{"source":10,"target":13,"value":2},{"source":10,"target":15,"value":1},{"source":11,"target":12,"value":4},{"source":11,"target":13,"value":2},{"source":11,"target":14,"value":2},{"source":12,"target":13,"value":5},{"source":12,"target":15,"value":2},{"source":13,"target":15,"value":2},{"source":14,"target":15,"value":2}]},{"epi":16,"nodes":[{"name":"노을","size":3},{"name":"덕선","size":5.08},{"name":"덕선모","size":4.25},{"name":"덕선부","size":3.91},{"name":"동룡","size":5.19},{"name":"미옥","size":3.4},{"name":"보라","size":3.91},{"name":"선우","size":4.94},{"name":"선우모","size":4.79},{"name":"정봉","size":3.91},{"name":"정환","size":4.79},{"name":"정환모","size":4.94},{"name":"정환부","size":4.38},{"name":"택이","size":4.38},{"name":"택이부","size":4.25}],"edges":[{"source":0,"target":1,"value":2},{"source":0,"target":2,"value":2},{"source":0,"target":3,"value":2},{"source":0,"target":6,"value":1},{"source":1,"target":2,"value":3},{"source":1,"target":3,"value":2},{"source":1,"target":4,"value":6},{"source":1,"target":5,"value":1},{"source":1,"target":6,"value":2},{"source":1,"target":7,"value":3},{"source":1,"target":9,"value":1},{"source":1,"target":10,"value":3},{"source":1,"target":13,"value":4},{"source":2,"target":3,"value":2},{"source":2,"target":6,"value":2},{"source":2,"target":8,"value":4},{"source":2,"target":9,"value":1},{"source":2,"target":11,"value":4},{"source":3,"target":6,"value":2},{"source":3,"target":12,"value":2},{"source":3,"target":14,"value":2},{"source":4,"target":7,"value":12},{"source":4,"target":8,"value":2},{"source":4,"target":10,"value":10},{"source":4,"target":11,"value":3},{"source":4,"target":13,"value":2},{"source":5,"target":9,"value":2},{"source":6,"target":7,"value":2},{"source":7,"target":10,"value":10},{"source":7,"target":13,"value":2},{"source":8,"target":9,"value":1},{"source":8,"target":11,"value":9},{"source":8,"target":12,"value":2},{"source":8,"target":14,"value":3},{"source":9,"target":10,"value":1},{"source":9,"target":11,"value":1},{"source":10,"target":13,"value":2},{"source":11,"target":12,"value":6},{"source":12,"target":14,"value":2},{"source":13,"target":14,"value":2}]},{"epi":17,"nodes":[{"name":"노을","size":4.25},{"name":"덕선","size":5.39},{"name":"덕선모","size":4.5},{"name":"덕선부","size":4.61},{"name":"동룡","size":3.91},{"name":"동룡부","size":3.69},{"name":"미옥","size":2.3},{"name":"보라","size":3.4},{"name":"선우","size":4.7},{"name":"선우모","size":4.7},{"name":"자현","size":3},{"name":"정봉","size":4.61},{"name":"정환","size":5.01},{"name":"정환모","size":5.01},{"name":"정환부","size":4.87},{"name":"택이","size":4.5},{"name":"택이부","size":4.5}],"edges":[{"source":0,"target":1,"value":5},{"source":0,"target":2,"value":3},{"source":0,"target":3,"value":4},{"source":0,"target":4,"value":1},{"source":1,"target":2,"value":2},{"source":1,"target":3,"value":5},{"source":1,"target":4,"value":4},{"source":1,"target":5,"value":2},{"source":1,"target":6,"value":1},{"source":1,"target":7,"value":1},{"source":1,"target":8,"value":5},{"source":1,"target":9,"value":1},{"source":1,"target":10,"value":2},{"source":1,"target":11,"value":2},{"source":1,"target":12,"value":4},{"source":1,"target":15,"value":5},{"source":2,"target":3,"value":3},{"source":2,"target":9,"value":3},{"source":2,"target":11,"value":1},{"source":2,"target":13,"value":4},{"source":2,"target":14,"value":1},{"source":3,"target":5,"value":2},{"source":3,"target":14,"value":2},{"source":3,"target":16,"value":2},{"source":4,"target":8,"value":4},{"source":4,"target":12,"value":4},{"source":4,"target":15,"value":2},{"source":5,"target":14,"value":2},{"source":5,"target":16,"value":2},{"source":7,"target":8,"value":2},{"source":8,"target":9,"value":3},{"source":8,"target":12,"value":5},{"source":8,"target":15,"value":5},{"source":8,"target":16,"value":1},{"source":9,"target":12,"value":1},{"source":9,"target":13,"value":4},{"source":9,"target":14,"value":1},{"source":9,"target":15,"value":1},{"source":9,"target":16,"value":5},{"source":11,"target":12,"value":7},{"source":11,"target":13,"value":3},{"source":11,"target":14,"value":3},{"source":12,"target":13,"value":4},{"source":12,"target":14,"value":3},{"source":12,"target":15,"value":3},{"source":12,"target":16,"value":1},{"source":13,"target":14,"value":11},{"source":14,"target":16,"value":2},{"source":15,"target":16,"value":3}]},{"epi":18,"nodes":[{"name":"노을","size":3.69},{"name":"덕선","size":5.25},{"name":"덕선모","size":4.7},{"name":"덕선부","size":3.91},{"name":"동룡","size":4.87},{"name":"동룡부","size":2.3},{"name":"미옥","size":2.3},{"name":"보라","size":4.25},{"name":"선우","size":5.14},{"name":"선우모","size":4.94},{"name":"정봉","size":3.4},{"name":"정환","size":5.52},{"name":"정환모","size":4.61},{"name":"정환부","size":4.09},{"name":"택이","size":4.7},{"name":"택이부","size":4.38}],"edges":[{"source":0,"target":2,"value":2},{"source":0,"target":3,"value":2},{"source":0,"target":7,"value":2},{"source":0,"target":9,"value":1},{"source":0,"target":11,"value":1},{"source":1,"target":2,"value":3},{"source":1,"target":3,"value":1},{"source":1,"target":4,"value":8},{"source":1,"target":7,"value":2},{"source":1,"target":8,"value":7},{"source":1,"target":11,"value":13},{"source":1,"target":14,"value":7},{"source":2,"target":3,"value":5},{"source":2,"target":7,"value":1},{"source":2,"target":9,"value":5},{"source":2,"target":12,"value":3},{"source":2,"target":13,"value":1},{"source":2,"target":15,"value":1},{"source":3,"target":7,"value":1},{"source":3,"target":9,"value":1},{"source":4,"target":8,"value":7},{"source":4,"target":11,"value":13},{"source":4,"target":14,"value":6},{"source":5,"target":15,"value":1},{"source":6,"target":10,"value":1},{"source":6,"target":11,"value":1},{"source":7,"target":8,"value":3},{"source":7,"target":9,"value":1},{"source":8,"target":9,"value":4},{"source":8,"target":11,"value":9},{"source":8,"target":14,"value":6},{"source":8,"target":15,"value":2},{"source":9,"target":12,"value":4},{"source":9,"target":13,"value":2},{"source":9,"target":14,"value":3},{"source":9,"target":15,"value":7},{"source":10,"target":11,"value":1},{"source":10,"target":12,"value":2},{"source":10,"target":13,"value":2},{"source":11,"target":12,"value":4},{"source":11,"target":13,"value":2},{"source":11,"target":14,"value":6},{"source":12,"target":13,"value":6},{"source":12,"target":15,"value":2},{"source":13,"target":15,"value":2},{"source":14,"target":15,"value":2}]},{"epi":19,"nodes":[{"name":"노을","size":4.25},{"name":"덕선","size":5.14},{"name":"덕선모","size":5.08},{"name":"덕선부","size":4.79},{"name":"동룡","size":3.69},{"name":"동룡부","size":3.69},{"name":"미옥","size":3.4},{"name":"보라","size":4.61},{"name":"선우","size":4.38},{"name":"선우모","size":4.38},{"name":"자현","size":3},{"name":"정봉","size":4.5},{"name":"정환","size":4.7},{"name":"정환모","size":4.87},{"name":"정환부","size":4.38},{"name":"택이","size":4.87},{"name":"택이부","size":3.69}],"edges":[{"source":0,"target":1,"value":6},{"source":0,"target":2,"value":4},{"source":0,"target":3,"value":4},{"source":0,"target":4,"value":2},{"source":0,"target":5,"value":2},{"source":0,"target":7,"value":6},{"source":0,"target":8,"value":2},{"source":0,"target":9,"value":2},{"source":0,"target":10,"value":1},{"source":0,"target":11,"value":1},{"source":0,"target":12,"value":2},{"source":0,"target":13,"value":2},{"source":0,"target":14,"value":2},{"source":0,"target":15,"value":2},{"source":0,"target":16,"value":1},{"source":1,"target":2,"value":5},{"source":1,"target":3,"value":6},{"source":1,"target":4,"value":3},{"source":1,"target":5,"value":2},{"source":1,"target":6,"value":1},{"source":1,"target":7,"value":6},{"source":1,"target":8,"value":3},{"source":1,"target":9,"value":3},{"source":1,"target":10,"value":2},{"source":1,"target":11,"value":1},{"source":1,"target":12,"value":3},{"source":1,"target":13,"value":3},{"source":1,"target":14,"value":3},{"source":1,"target":15,"value":10},{"source":1,"target":16,"value":2},{"source":2,"target":3,"value":10},{"source":2,"target":4,"value":3},{"source":2,"target":5,"value":4},{"source":2,"target":7,"value":4},{"source":2,"target":8,"value":2},{"source":2,"target":9,"value":7},{"source":2,"target":10,"value":1},{"source":2,"target":11,"value":3},{"source":2,"target":12,"value":3},{"source":2,"target":13,"value":9},{"source":2,"target":14,"value":4},{"source":2,"target":15,"value":1},{"source":2,"target":16,"value":2},{"source":3,"target":4,"value":3},{"source":3,"target":5,"value":2},{"source":3,"target":7,"value":4},{"source":3,"target":8,"value":1},{"source":3,"target":9,"value":3},{"source":3,"target":10,"value":1},{"source":3,"target":11,"value":2},{"source":3,"target":12,"value":3},{"source":3,"target":13,"value":4},{"source":3,"target":14,"value":4},{"source":3,"target":15,"value":1},{"source":3,"target":16,"value":3},{"source":4,"target":5,"value":2},{"source":4,"target":7,"value":2},{"source":4,"target":8,"value":2},{"source":4,"target":9,"value":2},{"source":4,"target":10,"value":1},{"source":4,"target":11,"value":2},{"source":4,"target":12,"value":4},{"source":4,"target":13,"value":3},{"source":4,"target":14,"value":1},{"source":4,"target":15,"value":2},{"source":4,"target":16,"value":1},{"source":5,"target":7,"value":3},{"source":5,"target":8,"value":2},{"source":5,"target":9,"value":3},{"source":5,"target":10,"value":1},{"source":5,"target":11,"value":2},{"source":5,"target":12,"value":2},{"source":5,"target":13,"value":4},{"source":5,"target":14,"value":2},{"source":5,"target":15,"value":1},{"source":5,"target":16,"value":1},{"source":6,"target":10,"value":1},{"source":6,"target":11,"value":2},{"source":7,"target":8,"value":6},{"source":7,"target":9,"value":3},{"source":7,"target":10,"value":1},{"source":7,"target":11,"value":1},{"source":7,"target":12,"value":2},{"source":7,"target":13,"value":3},{"source":7,"target":14,"value":2},{"source":7,"target":15,"value":2},{"source":7,"target":16,"value":1},{"source":8,"target":9,"value":2},{"source":8,"target":10,"value":1},{"source":8,"target":12,"value":3},{"source":8,"target":13,"value":2},{"source":8,"target":15,"value":3},{"source":8,"target":16,"value":1},{"source":9,"target":10,"value":1},{"source":9,"target":11,"value":1},{"source":9,"target":12,"value":2},{"source":9,"target":13,"value":7},{"source":9,"target":14,"value":2},{"source":9,"target":15,"value":2},{"source":9,"target":16,"value":3},{"source":10,"target":12,"value":1},{"source":10,"target":13,"value":1},{"source":10,"target":15,"value":1},{"source":10,"target":16,"value":1},{"source":11,"target":12,"value":5},{"source":11,"target":13,"value":4},{"source":11,"target":14,"value":3},{"source":12,"target":13,"value":4},{"source":12,"target":14,"value":1},{"source":12,"target":15,"value":4},{"source":12,"target":16,"value":1},{"source":13,"target":14,"value":6},{"source":13,"target":15,"value":1},{"source":13,"target":16,"value":2},{"source":14,"target":16,"value":2},{"source":15,"target":16,"value":2}]},{"epi":20,"nodes":[{"name":"노을","size":4.61},{"name":"덕선","size":5.39},{"name":"덕선모","size":4.79},{"name":"덕선부","size":5.14},{"name":"동룡","size":4.25},{"name":"동룡부","size":2.3},{"name":"미옥","size":3.4},{"name":"보라","size":5.14},{"name":"선우","size":5.14},{"name":"선우모","size":4.7},{"name":"정봉","size":3.91},{"name":"정환","size":4.7},{"name":"정환모","size":5.01},{"name":"정환부","size":4.7},{"name":"택이","size":5.08},{"name":"택이부","size":4.61}],"edges":[{"source":0,"target":1,"value":5},{"source":0,"target":2,"value":4},{"source":0,"target":3,"value":7},{"source":0,"target":7,"value":3},{"source":0,"target":9,"value":3},{"source":0,"target":11,"value":1},{"source":0,"target":12,"value":3},{"source":0,"target":13,"value":2},{"source":0,"target":14,"value":1},{"source":0,"target":15,"value":3},{"source":1,"target":2,"value":2},{"source":1,"target":3,"value":4},{"source":1,"target":4,"value":4},{"source":1,"target":7,"value":3},{"source":1,"target":8,"value":5},{"source":1,"target":9,"value":3},{"source":1,"target":10,"value":1},{"source":1,"target":11,"value":4},{"source":1,"target":12,"value":2},{"source":1,"target":14,"value":13},{"source":1,"target":15,"value":2},{"source":2,"target":3,"value":6},{"source":2,"target":7,"value":4},{"source":2,"target":8,"value":1},{"source":2,"target":9,"value":7},{"source":2,"target":11,"value":1},{"source":2,"target":12,"value":8},{"source":2,"target":13,"value":3},{"source":2,"target":14,"value":1},{"source":2,"target":15,"value":4},{"source":3,"target":4,"value":2},{"source":3,"target":5,"value":1},{"source":3,"target":7,"value":8},{"source":3,"target":8,"value":1},{"source":3,"target":9,"value":4},{"source":3,"target":11,"value":1},{"source":3,"target":12,"value":4},{"source":3,"target":13,"value":5},{"source":3,"target":14,"value":1},{"source":3,"target":15,"value":6},{"source":4,"target":5,"value":1},{"source":4,"target":7,"value":1},{"source":4,"target":8,"value":3},{"source":4,"target":9,"value":1},{"source":4,"target":10,"value":1},{"source":4,"target":11,"value":4},{"source":4,"target":12,"value":2},{"source":4,"target":13,"value":2},{"source":4,"target":14,"value":4},{"source":5,"target":13,"value":1},{"source":6,"target":10,"value":3},{"source":7,"target":8,"value":7},{"source":7,"target":9,"value":1},{"source":7,"target":15,"value":1},{"source":8,"target":9,"value":3},{"source":8,"target":11,"value":5},{"source":8,"target":14,"value":4},{"source":8,"target":15,"value":4},{"source":9,"target":10,"value":1},{"source":9,"target":11,"value":2},{"source":9,"target":12,"value":7},{"source":9,"target":13,"value":2},{"source":9,"target":14,"value":2},{"source":9,"target":15,"value":6},{"source":10,"target":11,"value":1},{"source":10,"target":12,"value":2},{"source":10,"target":13,"value":1},{"source":10,"target":14,"value":1},{"source":11,"target":12,"value":5},{"source":11,"target":13,"value":4},{"source":11,"target":14,"value":6},{"source":11,"target":15,"value":2},{"source":12,"target":13,"value":8},{"source":12,"target":14,"value":3},{"source":12,"target":15,"value":3},{"source":13,"target":14,"value":2},{"source":13,"target":15,"value":3},{"source":14,"target":15,"value":2}]}]}